[
  {
    "id": "rbs-optimizer-pro",
    "name": "RBS Optimizer Pro",
    "version": "1.0.0",
    "category": "Optimization",
    "categories": ["Optimization", "System Tools"],
    "description": "The ultimate free Windows optimization suite. Clean junk files, manage startup programs, boost performance, and monitor your system in real time — all in one polished application.",
    "fileSize": "~23 MB",
    "downloadUrl": "https://github.com/baljinder21/RBSsoftware/releases/download/v1.0.0/RBSOptimizerProRelease.zip",
    "downloadType": "external",
    "screenshot": null,
    "screenshotPath": "",
    "visible": true,
    "released": "2025-01-01",
    "downloads": 0,
    "features": [
      { "icon": "🧹", "title": "Deep Junk Cleaner",   "desc": "Remove temporary files, cache, old logs, and other system clutter safely and automatically." },
      { "icon": "🚀", "title": "Startup Manager",      "desc": "Control which programs launch at startup. Disable unnecessary entries to reduce boot time." },
      { "icon": "📊", "title": "Performance Monitor",  "desc": "Real-time graphs for CPU, RAM, and disk usage so you always know what's running." },
      { "icon": "⚙️", "title": "One-Click Optimize",   "desc": "Single button runs a full system tune-up — clean, optimize, and boost all at once." },
      { "icon": "🛡️", "title": "Privacy First",        "desc": "No telemetry, no data collection, no internet required. Your data stays on your machine." },
      { "icon": "🎨", "title": "Modern Interface",     "desc": "Clean, dark-themed UI that is intuitive for beginners and powerful for advanced users." }
    ],
    "sysReqs": [
      "Windows 10 or Windows 11 (64-bit)",
      "50 MB free disk space",
      "2 GB RAM minimum (4 GB recommended)",
      "1 GHz or faster processor",
      "No internet required to run",
      "Administrator rights for full features"
    ],
    "changelog": [
      { "version": "1.0.0", "date": "2025-01-01", "notes": ["Initial release", "Junk cleaner, startup manager, performance monitor", "One-click optimize mode", "Dark mode UI"] }
    ]
  },
  {
    "id": "rbs-voice-cloner",
    "name": "RBS Voice Cloner",
    "version": "1.0.0",
    "category": "AI Tools",
    "categories": ["AI Tools", "Audio"],
    "description": "Clone any voice with just a 5-second audio sample. Powered by XTTS v2 AI engine, generate natural-sounding speech in 28+ languages — completely free, runs locally on your PC.",
    "fileSize": "~248 MB",
    "downloadUrl": "https://github.com/baljinder21/RBSsoftware/releases/download/v1.0.0/RBSVoiceCloner_Setup.zip",
    "downloadType": "external",
    "screenshot": null,
    "screenshotPath": "",
    "visible": true,
    "released": "2026-04-12",
    "downloads": 0,
    "features": [
      { "icon": "🎙️", "title": "Voice Cloning",        "desc": "Clone any voice from a 5-30 second audio sample with stunning realism using XTTS v2." },
      { "icon": "🌍", "title": "28+ Languages",         "desc": "Generate speech in English, Spanish, French, German, Hindi, Japanese, Chinese, and many more." },
      { "icon": "📝", "title": "Text to Speech",        "desc": "Convert any text to natural speech using your cloned voice profiles." },
      { "icon": "🎚️", "title": "Audio Editor",          "desc": "Built-in audio editor with waveform view, trim, noise reduction and pitch control." },
      { "icon": "⚡", "title": "GPU Accelerated",       "desc": "Runs on your RTX GPU via CUDA for ultra-fast generation — CPU fallback for other PCs." },
      { "icon": "🔒", "title": "100% Offline",          "desc": "After the first model download, everything runs locally. No cloud, no data sent anywhere." }
    ],
    "sysReqs": [
      "Windows 10 or Windows 11 (64-bit)",
      "8 GB RAM minimum (16 GB recommended)",
      "4 GB free disk space (10 GB recommended for models)",
      "Internet connection required for first-time model download (~2 GB)",
      "NVIDIA GPU with CUDA recommended (CPU works but slower)",
      "Administrator rights for installation"
    ],
    "changelog": [
      { "version": "1.0.0", "date": "2026-04-12", "notes": ["Initial release", "XTTS v2 voice cloning engine", "28+ language support", "Built-in audio editor", "Batch processing", "GPU acceleration via CUDA"] }
    ]
  },
  {
    "id": "life-dashboard",
    "name": "Life Dashboard",
    "version": "1.0.0",
    "category": "Productivity",
    "categories": ["Productivity", "Lifestyle"],
    "description": "Your all-in-one personal productivity command center. 16 powerful widgets — track habits, tasks, finances, weather, sleep, diet and more — all in one beautiful dashboard.",
    "fileSize": "~104 MB",
    "downloadUrl": "https://github.com/baljinder21/RBSsoftware/releases/download/v1.0.0/Life.Dashboard.Setup.1.0.0.zip",
    "downloadType": "external",
    "screenshot": null,
    "screenshotPath": "",
    "visible": true,
    "released": "2026-04-14",
    "downloads": 0,
    "features": [
      { "icon": "✅", "title": "Tasks & Habits",      "desc": "To-do list with priorities and a daily habit tracker with streak counter to keep you on track." },
      { "icon": "💰", "title": "Finance Tracker",     "desc": "Log income and expenses with visual charts to understand where your money goes." },
      { "icon": "🌤️", "title": "Live Weather",        "desc": "Real-time weather with a 3-day forecast for any city in the world." },
      { "icon": "🎯", "title": "Goals & Countdown",   "desc": "Set long-term goals with progress bars and count down to important events." },
      { "icon": "🍎", "title": "Health Tracking",     "desc": "Track water intake, sleep quality, and diet plans with country-based meal templates." },
      { "icon": "🧩", "title": "16 Widgets",          "desc": "Clock, calendar, notes, Pomodoro timer, RSS news, quick links, motivational quotes and more." }
    ],
    "sysReqs": [
      "Windows 10 or Windows 11 (64-bit)",
      "100 MB free disk space",
      "4 GB RAM minimum",
      "Internet connection for weather and news widgets",
      "No administrator rights required"
    ],
    "changelog": [
      { "version": "1.0.0", "date": "2026-04-14", "notes": ["Initial release", "16 widgets including tasks, habits, finance, weather, sleep, diet", "Drag and resize widgets", "All data saved locally"] }
    ]
  },
  {
    "id": "rbs-pc-cleaner",
    "name": "RBS PC Cleaner",
    "version": "1.0.0",
    "category": "Optimization",
    "categories": ["Optimization", "System Tools", "Utilities"],
    "description": "Honest Windows maintenance utility with real numbers, reversible changes, and no fake scores. Clean junk safely, manage startup, find duplicates, uninstall in bulk, apply 9 theme packs — and never touch the registry.",
    "fileSize": "~61 MB",
    "downloadUrl": "https://github.com/baljinder21/RBSsoftware/releases/download/v1.0.0/RBS.PC.Cleaner.zip",
    "downloadType": "external",
    "screenshot": null,
    "screenshotPath": "",
    "visible": true,
    "released": "2026-04-19",
    "downloads": 0,
    "features": [
      { "icon": "🧽", "title": "Safe Junk Cleaner",    "desc": "Temp, recycle bin, Windows Update cache, prefetch, logs — each rated Safe / Caution / Risky, nothing deleted without confirmation." },
      { "icon": "🌐", "title": "Browser Cleaner",      "desc": "Clears cache, cookies, history for Chrome, Edge, Firefox, Brave, Opera. Saved passwords are reported but never deleted." },
      { "icon": "📦", "title": "App Cache Cleaner",    "desc": "Wipes Discord, Microsoft Teams, Spotify, VS Code, Slack, Zoom cache in one click." },
      { "icon": "📊", "title": "Disk Analyzer",        "desc": "Read-only folder tree — see exactly what is using your space and drill down click by click." },
      { "icon": "🔍", "title": "Duplicate Finder",     "desc": "Hash-based duplicate detection, always keeps the oldest file, auto-skips Windows and Program Files." },
      { "icon": "🗑️", "title": "Bulk Uninstaller",     "desc": "Tick multiple installed programs and uninstall in sequence — silent mode when supported." },
      { "icon": "🚀", "title": "Startup Manager",      "desc": "Toggle any startup entry on/off. Disabled entries are parked in a sibling key — fully reversible." },
      { "icon": "🎮", "title": "Gaming Mode",          "desc": "One click: safe clean + memory trim + High-Performance power plan + suspend background apps. Resume brings everything back." },
      { "icon": "🎨", "title": "9 Theme Packs",        "desc": "Real icon packs + matching 2560×1440 wallpapers + taskbar accent. Reversible with one click — Restore Original." },
      { "icon": "⏰", "title": "Scheduler",            "desc": "Daily or weekly silent auto-clean via Windows Task Scheduler." },
      { "icon": "🛡️", "title": "Safety Gate",          "desc": "Blocks deletion inside C:\\Windows, Program Files, ProgramData, drive roots — and never scans the registry." },
      { "icon": "💼", "title": "Portable Mode",        "desc": "Store settings + backups next to the exe — perfect for USB sticks and IT technicians." }
    ],
    "sysReqs": [
      "Windows 10 or Windows 11 (64-bit)",
      "150 MB free disk space",
      "2 GB RAM minimum (4 GB recommended)",
      "No Python installation required — everything bundled",
      "Administrator rights needed for drive-icon overrides, HKLM startup entries, and Windows Temp cleanup",
      "Installer (recommended) or portable ZIP — both supported"
    ],
    "changelog": [
      { "version": "1.0.0", "date": "2026-04-19", "notes": ["Initial public release", "Junk, browser, and app cache cleaners with Safe/Caution/Risky ratings", "Disk analyzer and hash-based duplicate finder", "Bulk uninstaller with silent-mode support", "Startup manager with reversible disable", "Gaming Mode with Resume button", "9 theme packs (Monochrome, Neon, Minimal, Retro, Cyberpunk, Ocean, Sunset, Forest, Windows Default)", "Scheduled auto-clean via Task Scheduler", "Portable mode and installer options", "Central safety gate — never scans or modifies the registry"] }
    ]
  }
]
